tailwindcss/__init__.py
tailwindcss/apps.py
tailwindcss/signals.py
tailwindcss/tests.py
tailwindcss/management/__init__.py
tailwindcss/management/commands/__init__.py
tailwindcss/management/commands/refreshtailwindcss.py
tailwindcss/templatetags/__init__.py
tailwindcss/templatetags/tailwindcss.py
django_tailwindcss-0.3.3.dist-info/LICENSE
django_tailwindcss-0.3.3.dist-info/METADATA
django_tailwindcss-0.3.3.dist-info/WHEEL
django_tailwindcss-0.3.3.dist-info/top_level.txt
django_tailwindcss-0.3.3.dist-info/RECORD
