Metadata-Version: 2.1
Name: django-tailwindcss
Version: 0.3.3
Summary: Develop with Tailwind CSS in Django flavour.
Home-page: https://github.com/veoco/django-tailwindcss
Author: Veoco
Author-email: one@nomox.cn
License: UNKNOWN
Platform: UNKNOWN
Classifier: Programming Language :: Python :: 3
Classifier: License :: OSI Approved :: MIT License
Classifier: Operating System :: OS Independent
License-File: LICENSE
